{
  "collection_metadata": {
    "collection_date": "2025-08-17T19:10:18.265997",
    "total_queries": 208,
    "target_per_query": 250,
    "total_target_count": 52000,
    "videos_collected_current_session": 383,
    "total_videos_in_file": 5322,
    "target_achievement_rate": "0.74%",
    "total_videos_evaluated": 1662,
    "total_videos_with_children_voice": 383,
    "overall_efficiency": "23.04%"
  },
  "query_statistics": [
    {
      "query": "trẻ Việt Nam",
      "videos_collected": 4,
      "videos_reviewed": 55,
      "videos_evaluated": 30,
      "videos_with_children_voice": 4,
      "videos_vietnamese": 30,
      "videos_not_vietnamese": 0,
      "efficiency_rate": 7.2727272727272725,
      "children_voice_rate": 13.333333333333334,
      "vietnamese_rate": 100.0,
      "new_channels_found": 1
    },
    {
      "query": "bé Việt Nam",
      "videos_collected": 46,
      "videos_reviewed": 217,
      "videos_evaluated": 186,
      "videos_with_children_voice": 46,
      "videos_vietnamese": 186,
      "videos_not_vietnamese": 0,
      "efficiency_rate": 21.19815668202765,
      "children_voice_rate": 24.731182795698924,
      "vietnamese_rate": 100.0,
      "new_channels_found": 6
    },
    {
      "query": "em Việt Nam",
      "videos_collected": 3,
      "videos_reviewed": 55,
      "videos_evaluated": 31,
      "videos_with_children_voice": 3,
      "videos_vietnamese": 31,
      "videos_not_vietnamese": 0,
      "efficiency_rate": 5.454545454545454,
      "children_voice_rate": 9.67741935483871,
      "vietnamese_rate": 100.0,
      "new_channels_found": 7
    },
    {
      "query": "bé cấp 1",
      "videos_collected": 2,
      "videos_reviewed": 78,
      "videos_evaluated": 65,
      "videos_with_children_voice": 2,
      "videos_vietnamese": 65,
      "videos_not_vietnamese": 0,
      "efficiency_rate": 2.564102564102564,
      "children_voice_rate": 3.076923076923077,
      "vietnamese_rate": 100.0,
      "new_channels_found": 8
    },
    {
      "query": "bé 5 tuổi",
      "videos_collected": 16,
      "videos_reviewed": 83,
      "videos_evaluated": 59,
      "videos_with_children_voice": 16,
      "videos_vietnamese": 59,
      "videos_not_vietnamese": 0,
      "efficiency_rate": 19.27710843373494,
      "children_voice_rate": 27.11864406779661,
      "vietnamese_rate": 100.0,
      "new_channels_found": 9
    },
    {
      "query": "bé 6 tuổi",
      "videos_collected": 1,
      "videos_reviewed": 60,
      "videos_evaluated": 31,
      "videos_with_children_voice": 1,
      "videos_vietnamese": 31,
      "videos_not_vietnamese": 0,
      "efficiency_rate": 1.6666666666666667,
      "children_voice_rate": 3.225806451612903,
      "vietnamese_rate": 100.0,
      "new_channels_found": 10
    },
    {
      "query": "bé 7 tuổi",
      "videos_collected": 0,
      "videos_reviewed": 50,
      "videos_evaluated": 20,
      "videos_with_children_voice": 0,
      "videos_vietnamese": 20,
      "videos_not_vietnamese": 0,
      "efficiency_rate": 0.0,
      "children_voice_rate": 0.0,
      "vietnamese_rate": 100.0,
      "new_channels_found": 10
    },
    {
      "query": "bé 8 tuổi",
      "videos_collected": 11,
      "videos_reviewed": 98,
      "videos_evaluated": 72,
      "videos_with_children_voice": 11,
      "videos_vietnamese": 72,
      "videos_not_vietnamese": 0,
      "efficiency_rate": 11.224489795918368,
      "children_voice_rate": 15.277777777777779,
      "vietnamese_rate": 100.0,
      "new_channels_found": 12
    },
    {
      "query": "bé 9 tuổi",
      "videos_collected": 8,
      "videos_reviewed": 113,
      "videos_evaluated": 92,
      "videos_with_children_voice": 8,
      "videos_vietnamese": 92,
      "videos_not_vietnamese": 0,
      "efficiency_rate": 7.079646017699115,
      "children_voice_rate": 8.695652173913043,
      "vietnamese_rate": 100.0,
      "new_channels_found": 15
    },
    {
      "query": "bé 10 tuổi",
      "videos_collected": 0,
      "videos_reviewed": 50,
      "videos_evaluated": 13,
      "videos_with_children_voice": 0,
      "videos_vietnamese": 13,
      "videos_not_vietnamese": 0,
      "efficiency_rate": 0.0,
      "children_voice_rate": 0.0,
      "vietnamese_rate": 100.0,
      "new_channels_found": 15
    },
    {
      "query": "trẻ em nói",
      "videos_collected": 11,
      "videos_reviewed": 67,
      "videos_evaluated": 29,
      "videos_with_children_voice": 11,
      "videos_vietnamese": 29,
      "videos_not_vietnamese": 0,
      "efficiency_rate": 16.417910447761194,
      "children_voice_rate": 37.93103448275862,
      "vietnamese_rate": 100.0,
      "new_channels_found": 19
    },
    {
      "query": "trẻ em chia sẻ",
      "videos_collected": 42,
      "videos_reviewed": 146,
      "videos_evaluated": 136,
      "videos_with_children_voice": 42,
      "videos_vietnamese": 136,
      "videos_not_vietnamese": 0,
      "efficiency_rate": 28.767123287671232,
      "children_voice_rate": 30.88235294117647,
      "vietnamese_rate": 100.0,
      "new_channels_found": 24
    },
    {
      "query": "bé chia sẻ",
      "videos_collected": 56,
      "videos_reviewed": 223,
      "videos_evaluated": 207,
      "videos_with_children_voice": 56,
      "videos_vietnamese": 207,
      "videos_not_vietnamese": 0,
      "efficiency_rate": 25.112107623318387,
      "children_voice_rate": 27.053140096618357,
      "vietnamese_rate": 100.0,
      "new_channels_found": 31
    },
    {
      "query": "trẻ em đối thoại",
      "videos_collected": 1,
      "videos_reviewed": 51,
      "videos_evaluated": 28,
      "videos_with_children_voice": 1,
      "videos_vietnamese": 28,
      "videos_not_vietnamese": 0,
      "efficiency_rate": 1.9607843137254901,
      "children_voice_rate": 3.571428571428571,
      "vietnamese_rate": 100.0,
      "new_channels_found": 32
    },
    {
      "query": "bé đối thoại",
      "videos_collected": 4,
      "videos_reviewed": 56,
      "videos_evaluated": 37,
      "videos_with_children_voice": 4,
      "videos_vietnamese": 37,
      "videos_not_vietnamese": 0,
      "efficiency_rate": 7.142857142857142,
      "children_voice_rate": 10.81081081081081,
      "vietnamese_rate": 100.0,
      "new_channels_found": 34
    },
    {
      "query": "trẻ tự nhiên",
      "videos_collected": 3,
      "videos_reviewed": 58,
      "videos_evaluated": 55,
      "videos_with_children_voice": 3,
      "videos_vietnamese": 55,
      "videos_not_vietnamese": 0,
      "efficiency_rate": 5.172413793103448,
      "children_voice_rate": 5.454545454545454,
      "vietnamese_rate": 100.0,
      "new_channels_found": 35
    },
    {
      "query": "bé tự giới thiệu",
      "videos_collected": 99,
      "videos_reviewed": 256,
      "videos_evaluated": 244,
      "videos_with_children_voice": 99,
      "videos_vietnamese": 244,
      "videos_not_vietnamese": 0,
      "efficiency_rate": 38.671875,
      "children_voice_rate": 40.57377049180328,
      "vietnamese_rate": 100.0,
      "new_channels_found": 58
    },
    {
      "query": "trẻ giới thiệu",
      "videos_collected": 13,
      "videos_reviewed": 86,
      "videos_evaluated": 68,
      "videos_with_children_voice": 13,
      "videos_vietnamese": 68,
      "videos_not_vietnamese": 0,
      "efficiency_rate": 15.11627906976744,
      "children_voice_rate": 19.11764705882353,
      "vietnamese_rate": 100.0,
      "new_channels_found": 67
    },
    {
      "query": "em giới thiệu",
      "videos_collected": 21,
      "videos_reviewed": 85,
      "videos_evaluated": 78,
      "videos_with_children_voice": 21,
      "videos_vietnamese": 78,
      "videos_not_vietnamese": 0,
      "efficiency_rate": 24.705882352941178,
      "children_voice_rate": 26.923076923076923,
      "vietnamese_rate": 100.0,
      "new_channels_found": 73
    },
    {
      "query": "kỹ năng sống trẻ em",
      "videos_collected": 3,
      "videos_reviewed": 61,
      "videos_evaluated": 28,
      "videos_with_children_voice": 3,
      "videos_vietnamese": 28,
      "videos_not_vietnamese": 0,
      "efficiency_rate": 4.918032786885246,
      "children_voice_rate": 10.714285714285714,
      "vietnamese_rate": 100.0,
      "new_channels_found": 74
    },
    {
      "query": "bé làm thủ công",
      "videos_collected": 39,
      "videos_reviewed": 163,
      "videos_evaluated": 153,
      "videos_with_children_voice": 39,
      "videos_vietnamese": 153,
      "videos_not_vietnamese": 0,
      "efficiency_rate": 23.92638036809816,
      "children_voice_rate": 25.49019607843137,
      "vietnamese_rate": 100.0,
      "new_channels_found": 78
    }
  ],
  "query_list": [
    "trẻ Việt Nam",
    "bé Việt Nam",
    "em Việt Nam",
    "bé cấp 1",
    "bé 5 tuổi",
    "bé 6 tuổi",
    "bé 7 tuổi",
    "bé 8 tuổi",
    "bé 9 tuổi",
    "bé 10 tuổi",
    "trẻ em nói",
    "trẻ em chia sẻ",
    "bé chia sẻ",
    "trẻ em đối thoại",
    "bé đối thoại",
    "trẻ tự nhiên",
    "bé tự giới thiệu",
    "trẻ giới thiệu",
    "em giới thiệu",
    "kỹ năng sống trẻ em",
    "bé làm thủ công",
    "trẻ làm thủ công",
    "đồ thủ công bé",
    "bé nấu ăn",
    "trẻ nấu ăn",
    "em nấu ăn",
    "bé truyện cổ tích",
    "trẻ đọc sách",
    "bé đọc sách",
    "em đọc sách",
    "bé trò chơi",
    "trẻ phỏng vấn",
    "bé phỏng vấn",
    "em phỏng vấn",
    "bé chữ cái",
    "trẻ chữ cái",
    "bé số đếm",
    "trẻ số đếm",
    "bé màu sắc",
    "trẻ màu sắc",
    "bé con vật",
    "trẻ con vật",
    "bé gia đình",
    "trẻ gia đình",
    "bé trường học",
    "trẻ trường học",
    "bé an toàn",
    "trẻ giao thông",
    "bé cảm xúc",
    "trẻ cảm xúc",
    "bé thời tiết",
    "trẻ thời tiết",
    "bé các mùa",
    "trẻ các mùa",
    "bé nghề nghiệp",
    "trẻ nghề nghiệp",
    "bé văn hóa",
    "trẻ văn hóa",
    "bé bài hát",
    "bé học thơ",
    "trẻ học thơ",
    "bé câu đố",
    "trẻ câu đố",
    "bé thí nghiệm",
    "trẻ thí nghiệm",
    "bé học vẽ",
    "trẻ học vẽ",
    "bé học toán",
    "trẻ học toán",
    "bé khoa học",
    "trẻ khoa học",
    "bé giáo dục",
    "bé hoạt động",
    "POPS Kids trẻ em",
    "POPS Kids bé nói",
    "BabyBus trẻ em",
    "BabyBus bé nói",
    "BHMEDIA thiếu nhi",
    "BHMEDIA trẻ em",
    "NiDo Channel trẻ em",
    "NiDo Channel bé",
    "Like Nastya VNM",
    "Like Nastya trẻ em",
    "POPS Kids dạy bé",
    "BabyBus bé tập nói",
    "BHMEDIA truyện",
    "BHMEDIA cổ tích",
    "NiDo bé học",
    "Like Nastya vlog",
    "Farmees Việt Nam",
    "Farmees bài hát",
    "Heo Peppa",
    "Peppa Pig Việt",
    "Kênh Thiếu Nhi",
    "BHMEDIA video",
    "POPS chương trình",
    "BabyBus hoạt hình",
    "trẻ em vlog",
    "bé vlog",
    "dạy bé nói",
    "bé học từ vựng",
    "bé ngữ pháp",
    "bé trò chơi học",
    "phản ứng bé",
    "trẻ em đối thoại",
    "bé giọng Bắc",
    "bé giọng Nam",
    "video trẻ tự quay",
    "bé tự quay",
    "trẻ chia sẻ kinh nghiệm",
    "bé kinh nghiệm",
    "bé bài hát tương tác",
    "trẻ kể chuyện",
    "bé sáng tạo",
    "video thử thách",
    "bé thử thách",
    "bé câu chuyện",
    "trẻ thảo luận",
    "bé thảo luận",
    "video hướng dẫn",
    "bé hướng dẫn",
    "bé tình huống",
    "trẻ tự học",
    "bé tự học",
    "video tự làm",
    "bé làm đồ chơi",
    "bé hoạt động nhóm",
    "trẻ ước mơ",
    "bé ước mơ",
    "phát triển ngôn ngữ",
    "trẻ mầm non",
    "bé mầm non",
    "giao tiếp trẻ em",
    "dạy bé phát âm",
    "luyện nói trẻ",
    "bé vốn từ",
    "trẻ diễn đạt",
    "bé diễn đạt",
    "kích thích nói",
    "bé câu tiếng Việt",
    "trẻ ngữ điệu",
    "bé ngữ điệu",
    "bé kể chuyện",
    "trẻ sơ sinh",
    "bé 1 tuổi",
    "bé 2 tuổi",
    "bé tập nói",
    "trẻ 3 tuổi",
    "trẻ 4 tuổi",
    "trẻ 5 tuổi học",
    "trẻ 6 tuổi học",
    "học sinh tiểu học",
    "trẻ mầm non giao tiếp",
    "video tập nói",
    "mẫu giáo",
    "dạy trẻ nhỏ",
    "phát triển lời nói cho trẻ em Việt Nam",
    "trẻ em",
    "bé nói",
    "thiếu nhi",
    "em bé",
    "con nói",
    "bé tập nói",
    "trẻ nói",
    "bé học",
    "trẻ học",
    "em học",
    "bé chơi",
    "trẻ chơi",
    "em chơi",
    "bé làm",
    "trẻ làm",
    "em làm",
    "video trẻ em",
    "video bé",
    "video thiếu nhi",
    "hoạt hình trẻ em",
    "hoạt hình bé",
    "phim trẻ em",
    "phim bé",
    "truyện trẻ em",
    "truyện bé",
    "bài hát trẻ em",
    "bài hát bé",
    "đồng dao",
    "ca dao",
    "thơ thiếu nhi",
    "câu chuyện trẻ em",
    "câu chuyện bé",
    "giáo dục trẻ em",
    "giáo dục bé",
    "học tập trẻ em",
    "học tập bé",
    "vui chơi trẻ em",
    "vui chơi bé",
    "giao tiếp trẻ em",
    "giao tiếp bé",
    "đối thoại trẻ em",
    "đối thoại bé",
    "nói chuyện trẻ em",
    "nói chuyện bé",
    "chia sẻ trẻ em",
    "chia sẻ bé",
    "kể chuyện trẻ em",
    "kể chuyện bé",
    "hát trẻ em",
    "hát bé",
    "POPS Kids"
  ]
}